Metadata-Version: 2.1
Name: sklearmpi
Version: 0.1.1
Summary: Una descripción breve de tu biblioteca
Home-page: https://github.com/tu_usuario/mi_libreria
Author: Tu Nombre
Author-email: tu_email@ejemplo.com
